mutwo/csound_converters/__init__.py
mutwo/csound_converters/configurations.py
mutwo/csound_converters/constants.py
mutwo/csound_converters/csound.py
mutwo.ext_csound-0.5.0.dist-info/LICENSE
mutwo.ext_csound-0.5.0.dist-info/METADATA
mutwo.ext_csound-0.5.0.dist-info/WHEEL
mutwo.ext_csound-0.5.0.dist-info/top_level.txt
mutwo.ext_csound-0.5.0.dist-info/RECORD
