Metadata-Version: 2.1
Name: mutwo.ext-csound
Version: 0.5.0
Summary: csound extension for event based framework for generative art
Home-page: https://github.com/mutwo-org/mutwo.ext-csound
Author: Levin Eric Zimmermann
Author-email: levin.eric.zimmermann@posteo.eu
License: GPL
Project-URL: Documentation, https://mutwo.readthedocs.io/en/latest/
Platform: UNKNOWN
Requires-Python: >=3.9, <4
License-File: LICENSE
Requires-Dist: mutwo.ext-core (<1.0.0,>=0.55.0)
Requires-Dist: natsort (<6.0.0,>=5.3.3)
Provides-Extra: testing
Requires-Dist: nose ; extra == 'testing'
Requires-Dist: coveralls ; extra == 'testing'
